thutils/__init__.py
thutils/cache.py
thutils/common.py
thutils/environment.py
thutils/gfile.py
thutils/gtime.py
thutils/loader.py
thutils/logger.py
thutils/main.py
thutils/option.py
thutils/subprocwrapper.py
thutils-0.1.24.dist-info/DESCRIPTION.rst
thutils-0.1.24.dist-info/METADATA
thutils-0.1.24.dist-info/RECORD
thutils-0.1.24.dist-info/WHEEL
thutils-0.1.24.dist-info/metadata.json
thutils-0.1.24.dist-info/top_level.txt
