Metadata-Version: 2.0
Name: thutils
Version: 0.1.24
Summary: Personal python utility library
Home-page: https://github.com/thombashi/thutils
Author: Tsuyoshi Hombashi
Author-email: gogogo.vm@gmail.com
License: GNU Lesser General Public License v3 (LGPLv3)
Platform: UNKNOWN
Classifier: Development Status :: 3 - Alpha
Classifier: Intended Audience :: Developers
Classifier: License :: OSI Approved :: GNU Lesser General Public License v3 (LGPLv3)
Classifier: Operating System :: Microsoft :: Windows
Classifier: Operating System :: POSIX :: Linux
Classifier: Programming Language :: Python :: 2
Classifier: Programming Language :: Python :: 2.5
Classifier: Programming Language :: Python :: 2.6
Classifier: Programming Language :: Python :: 2.7
Classifier: Programming Language :: Python :: 3
Classifier: Programming Language :: Python :: 3.3
Classifier: Programming Language :: Python :: 3.4
Classifier: Programming Language :: Python :: 3.5
Classifier: Topic :: Software Development :: Libraries
Classifier: Topic :: Software Development :: Libraries :: Python Modules
Requires-Dist: DataProperty
Requires-Dist: path.py
Requires-Dist: pathvalidate
Requires-Dist: python-magic
Requires-Dist: six
